ratel_runner/__init__.py
ratel_runner/helper/build/__init__.py
ratel_runner/helper/build/build.py
ratel_runner/helper/build/build_libceed.py
ratel_runner/helper/build/build_petsc.py
ratel_runner/helper/build/build_ratel.py
ratel_runner/helper/build/git.py
ratel_runner/helper/build/machines/reconfigure_lassen.py
ratel_runner/helper/build/machines/reconfigure_tioga.py
ratel_runner/helper/build/machines/reconfigure_tuolumne.py
ratel_runner/helper/config.py
ratel_runner/helper/experiment.py
ratel_runner/helper/flux/__init__.py
ratel_runner/helper/flux/fluid.py
ratel_runner/helper/flux/flux.py
ratel_runner/helper/flux/machines.py
ratel_runner/helper/flux/mnemonicode/LICENSE
ratel_runner/helper/flux/mnemonicode/__init__.py
ratel_runner/helper/flux/mnemonicode/__init__.pyi
ratel_runner/helper/flux/mnemonicode/_utils.py
ratel_runner/helper/flux/mnemonicode/_utils.pyi
ratel_runner/helper/flux/mnemonicode/_wordlist.py
ratel_runner/helper/flux/mnemonicode/py.typed
ratel_runner/helper/main.py
ratel_runner/helper/utilities.py
ratel_runner/main.py
ratel_runner/mpm/experiments/efficiency.py
ratel_runner/mpm/experiments/press_boundary.py
ratel_runner/mpm/experiments/press_common.py
ratel_runner/mpm/experiments/press_no_air.py
ratel_runner/mpm/experiments/press_sticky_air.py
ratel_runner/mpm/experiments/yml/common_solver.yml
ratel_runner/mpm/experiments/yml/press_no_air_damage.yml
ratel_runner/mpm/experiments/yml/press_no_air_monoclinic.yml
ratel_runner/mpm/experiments/yml/press_no_air_neo_hookean.yml
ratel_runner/mpm/experiments/yml/press_no_air_triclinic.yml
ratel_runner/mpm/experiments/yml/press_sticky_air.yml
ratel_runner/mpm/local.py
ratel_runner/mpm/main.py
ratel_runner/mpm/sweep.py
ratel_runner/postprocess/main.py
ratel_runner/postprocess/plot/pole_diagram.py
ratel_runner-0.6.0.dist-info/licenses/LICENSE
ratel_runner-0.6.0.dist-info/WHEEL
ratel_runner-0.6.0.dist-info/entry_points.txt
ratel_runner-0.6.0.dist-info/METADATA
ratel_runner-0.6.0.dist-info/RECORD
