Metadata-Version: 2.4
Name: ratel-runner
Version: 0.6.0
Summary: Utilities for building and running the Ratel finite element library
Keywords: Ratel,finite elements,scientific computing,HPC,material point method,mpm
Author: Zach Atkins
Author-email: Zach Atkins <zach.atkins@colorado.edu>
License-Expression: MIT
License-File: LICENSE
Classifier: Development Status :: 3 - Alpha
Classifier: Intended Audience :: Developers
Classifier: Topic :: Software Development :: Build Tools
Classifier: Programming Language :: Python :: 3
Classifier: Programming Language :: Python :: 3.9
Classifier: Programming Language :: Python :: 3.10
Classifier: Programming Language :: Python :: 3.11
Classifier: Programming Language :: Python :: 3.12
Classifier: Programming Language :: Python :: 3.13
Requires-Dist: typer>=0.15.2,<1.0.0
Requires-Dist: gmsh>=4.13.1,<5.0.0 ; extra == 'mpm'
Requires-Dist: pandas>=2.2.3,<3.0.0 ; extra == 'mpm'
Requires-Dist: pyyaml>=6.0.2,<7.0.0 ; extra == 'mpm'
Requires-Dist: matplotlib>=3.9.4 ; extra == 'postprocess'
Requires-Dist: numpy>=2.0.2 ; extra == 'postprocess'
Requires-Dist: orix>=0.13.0 ; extra == 'postprocess'
Requires-Dist: pyvista>=0.46.4 ; extra == 'postprocess'
Requires-Python: >=3.9, <4.0
Project-URL: Issues, https://github.com/zatkins-dev/ratel-runner/issues
Project-URL: Repository, https://github.com/zatkins-dev/ratel-runner
Provides-Extra: mpm
Provides-Extra: postprocess
